[
    {
        "location": "43.70587544,-72.2911665",
        "null": "2",
        "place": "my room. mid mass 405",
        "productivity": "3",
        "resp_time": 1366589813
    },
    {
        "location": "43.7031993,-72.2904444",
        "null": "2",
        "place": "my room midmass405",
        "productivity": "4",
        "resp_time": 1366690694
    },
    {
        "location": "43.47216071,-71.99885894",
        "noise": "2",
        "place": "foco",
        "productivity": "3",
        "resp_time": 1367359355
    }
]